LICENSE
mctinctools/__init__.py
mctinctools/__main__.py
mctinctools/apikey.py
mctinctools/console.py
mctinctools/display.py
mctinctools/presentation_functions.py
mctinctools-0.1.5.dist-info/entry_points.txt
mctinctools-0.1.5.dist-info/LICENSE
mctinctools-0.1.5.dist-info/WHEEL
mctinctools-0.1.5.dist-info/METADATA
mctinctools-0.1.5.dist-info/RECORD
