Metadata-Version: 2.1
Name: mctinctools
Version: 0.1.5
Summary: Common tools for our organization.
Home-page: https://github.com/forums34/mctinctools
License: MIT
Author: forums34
Author-email: greg.wendel@hey.com
Requires-Python: >=3.10,<4.0
Classifier: License :: OSI Approved :: MIT License
Classifier: Programming Language :: Python :: 3
Classifier: Programming Language :: Python :: 3.10
Requires-Dist: Faker (>=13.15.1,<14.0.0)
Requires-Dist: Jinja2 (>=3.1.2,<4.0.0)
Requires-Dist: PyPDF2 (>=2.8.1,<3.0.0)
Requires-Dist: click (>=8.1.3,<9.0.0)
Requires-Dist: interrogate (>=1.5.0,<2.0.0)
Requires-Dist: mdx-gh-links (>=0.3,<0.4)
Requires-Dist: mkdocs-gen-files (>=0.3.5,<0.4.0)
Requires-Dist: mkdocs-literate-nav (>=0.4.1,<0.5.0)
Requires-Dist: mkdocs-material (>=8.3.9,<9.0.0)
Requires-Dist: mkdocstrings (>=0.19.0,<0.20.0)
Requires-Dist: mkdocstrings-python (>=0.7.1,<0.8.0)
Requires-Dist: openpyxl (>=3.0.10,<4.0.0)
Requires-Dist: pandas (>=1.4.3,<2.0.0)
Requires-Dist: pdfforms (>=2.0.0,<3.0.0)
Requires-Dist: pdfminer (>=20191125,<20191126)
Requires-Dist: pdfminer.six (>=20220524,<20220525)
Requires-Dist: pdfplumber (>=0.7.4,<0.8.0)
Requires-Dist: pre-commit (>=2.20.0,<3.0.0)
Requires-Dist: pyarrow (>=8.0.0,<9.0.0)
Requires-Dist: pytest (>=7.1.2,<8.0.0)
Requires-Dist: python-dotenv (>=0.20.0,<0.21.0)
Requires-Dist: reportlab (>=3.6.11,<4.0.0)
Requires-Dist: rich (>=12.5.1,<13.0.0)
Project-URL: Repository, https://github.com/forums34/mctinctools.git
